swizz/__init__.py
swizz/layout.py
swizz/manim.py
swizz/plot.py
swizz/table.py
swizz/layouts/__init__.py
swizz/layouts/_registry.py
swizz/layouts/blocks.py
swizz/layouts/collection/__init__.py
swizz/layouts/collection/grid_stack.py
swizz/logging/logger.py
swizz/logging/wandb_analyzer.py
swizz/manims/__init__.py
swizz/manims/_registry.py
swizz/manims/code_evolution.py
swizz/manims/histograms_evolution.py
swizz/plots/__init__.py
swizz/plots/_registry.py
swizz/plots/base.py
swizz/plots/confusion_matrix.py
swizz/plots/dual_histogram_with_errorbars.py
swizz/plots/embedding_2d_plot.py
swizz/plots/function_percentile_plot.py
swizz/plots/heatmap.py
swizz/plots/horizontal_bar_plot.py
swizz/plots/percentile_curve_plot.py
swizz/plots/simple_bar_plot.py
swizz/plots/simple_multiple_std_lines.py
swizz/tables/__init__.py
swizz/tables/_registry.py
swizz/tables/df_to_latex.py
swizz/tables/grouped_block_latex.py
swizz/tables/large_results_grid.py
swizz/tables/multiple_grouped_cols.py
swizz/utils/__init__.py
swizz/utils/manims.py
swizz/utils/plot.py
swizz/utils/table.py
swizz-0.1.3.1.dist-info/licenses/LICENSE
swizz-0.1.3.1.dist-info/METADATA
swizz-0.1.3.1.dist-info/WHEEL
swizz-0.1.3.1.dist-info/top_level.txt
swizz-0.1.3.1.dist-info/RECORD
