Metadata-Version: 2.4
Name: swizz
Version: 0.1.3.1
Summary: Publication-ready plotting library for ML papers
Author-email: Lars Quaedvlieg <larsquaedvlieg@outlook.com>
License: MIT License
Project-URL: Homepage, https://github.com/lars-quaedvlieg/swizz
Project-URL: Documentation, https://lars-quaedvlieg.github.io/swizz/
Classifier: Programming Language :: Python :: 3
Classifier: License :: OSI Approved :: MIT License
Classifier: Operating System :: OS Independent
Requires-Python: >=3.10
License-File: LICENSE
Requires-Dist: matplotlib==3.10.3
Requires-Dist: seaborn==0.13.2
Requires-Dist: pandas==2.2.2
Requires-Dist: numpy==2.2.6
Requires-Dist: omegaconf==2.3.0
Requires-Dist: manim==0.19.0
Provides-Extra: docs
Requires-Dist: jupyter-book>=1.0.4.post1; extra == "docs"
Requires-Dist: Jinja2>=3.1; extra == "docs"
Dynamic: license-file
